{
    "data": {
        "sounds": [
            {
                "title": "Watery Desire",
                "content": "/sounds/Black_Ant_-_01_-_Fater_Lee.mp3",
                "author": "Paris Hilton",
                "source": "http://freemusicarchive.org/",
                "category": 1
            },
            {
                "title": "Harmonious Basketball",
                "content": "/sounds/BoxCat_Games_-_10_-_Epic_Song.mp3",
                "author": "John Travolta",
                "source": "http://freemusicarchive.org/",
                "category": 2
            },
            {
                "title": "Guttural Flame",
                "content": "/sounds/Broke_For_Free_-_01_-_Night_Owl.mp3",
                "author": "Dave Matthews",
                "source": "http://freemusicarchive.org/",
                "category": 3
            },
            {
                "title": "Robust Sofa",
                "content": "/sounds/Broke_For_Free_-_05_-_Something_Elated.mp3",
                "author": "LeBron James",
                "source": "http://freemusicarchive.org/",
                "category": 1
            },
            {
                "title": "Garrulous Iron",
                "content": "/sounds/Gillicuddy_-_05_-_Springish.mp3",
                "author": "Sean Penn",
                "source": "http://freemusicarchive.org/",
                "category": 2
            },
            {
                "title": "Snobbish Trade",
                "content": "/sounds/Jahzzar_-_05_-_Siesta.mp3",
                "author": "John Travolta",
                "source": "http://freemusicarchive.org/",
                "category": 3
            },
            {
                "title": "Impolite Attraction",
                "content": "/sounds/Jason_Shaw_-_RUNNING_WATERS.mp3",
                "author": "Ron Howard",
                "source": "http://freemusicarchive.org/",
                "category": 1
            },
            {
                "title": "Impartial Lunchroom",
                "content": "/sounds/Kai_Engel_-_04_-_Moonlight_Reprise.mp3",
                "author": "LeBron James",
                "source": "http://freemusicarchive.org/",
                "category": 2
            },
            {
                "title": "Snobbish Tail",
                "content": "/sounds/Monk_Turner__Fascinoma_-_01_-_Its_Your_Birthday.mp3",
                "author": "LeBron James",
                "source": "http://freemusicarchive.org/",
                "category": 3
            },
            {
                "title": "Detailed Jellyfish",
                "content": "/sounds/Podington_Bear_-_Starling.mp3",
                "author": "Chris Brown",
                "source": "http://freemusicarchive.org/",
                "category": 1
            },
            {
                "title": "Guiltless Glove",
                "content": "/sounds/The_Kyoto_Connection_-_09_-_Hachiko_The_Faithtful_Dog.mp3",
                "author": "Paris Hilton",
                "source": "http://freemusicarchive.org/",
                "category": 2
            },
            {
                "title": "Ubiquitous Sugar",
                "content": "/sounds/Tours_-_01_-_Enthusiast.mp3",
                "author": "Ray Romano",
                "source": "http://freemusicarchive.org/",
                "category": 3
            }
        ]
    }
}